{
  "journal_id": "J000657",
  "titles": [
    {
      "title": "Development, Growth & Differentiation",
      "language": "ja"
    }
  ],
  "journal_title_alias": null,
  "journal_url": null,
  "issns": [
    {
      "type": "linking",
      "issn": "1440169X"
    }
  ],
  "listed_in_doaj": null,
  "oa_type": null,
  "oa_type_notes": null,
  "non_embargo_oa": null,
  "applicability": null,
  "society": {
    "id": "S000548",
    "name": "日本発生生物学会",
    "name_en": null,
    "url": "http://www.jsdb.jp/",
    "contact_url": null,
    "meikan_url": "https://gakkai.scj.go.jp/organizations/G00692"
  },
  "publisher_policy": [
    {
      "article_version": "published",
      "copyright_owner": null,
      "licence": null,
      "archivability": null,
      "location": {
        "ir": null,
        "author": null,
        "funder": null,
        "non_commercial": null,
        "others": null
      },
      "embargo": {
        "general_months": null,
        "funded_months": null
      },
      "terms": {
        "copyright": null,
        "by": null,
        "link": null,
        "notes": null
      }
    },
    {
      "article_version": "accepted",
      "copyright_owner": null,
      "licence": null,
      "archivability": null,
      "location": {
        "ir": null,
        "author": null,
        "funder": null,
        "non_commercial": null,
        "others": null
      },
      "embargo": {
        "general_months": null,
        "funded_months": null
      },
      "terms": {
        "copyright": null,
        "by": null,
        "link": null,
        "notes": null
      }
    },
    {
      "article_version": "submitted",
      "copyright_owner": null,
      "licence": null,
      "archivability": null,
      "location": {
        "ir": null,
        "author": null,
        "funder": null,
        "non_commercial": null,
        "others": null
      },
      "embargo": null,
      "terms": {
        "copyright": null,
        "by": null,
        "link": null,
        "notes": null
      }
    }
  ],
  "policy_url": "http://onlinelibrary.wiley.com/journal/10.1111/%28ISSN%291440-169X/homepage/ForAuthors.html",
  "cdjournal": null,
  "updated_at": null,
  "sheet_updated_at": null
}