{
  "sheet_updated_at": "",
  "journal_id": "J001082",
  "journal_title": "日本小児腎臓病学会雑誌",
  "journal_title_alias": "",
  "journal_title_en": "Japanese journal of pediatric nephrology",
  "journal_url": "https://www.jstage.jst.go.jp/browse/jjpn/-char/ja",
  "issn_l": "09152245",
  "pissn": "09152245",
  "eissn": "18813933",
  "doaj": "DOAJ",
  "oa_type": "フルOAモデル",
  "oa_type_notes": "",
  "policy_url": "https://jspn01.umin.jp/gakkaishi/gakkaishi/rinri.html",
  "non_embargo_oa": "出版後即時OA可",
  "society_id": "S000901",
  "society_name": "日本小児腎臓病学会",
  "society_name_en": "",
  "society_url": "http://www.jspn.jp/",
  "society_contact_url": "",
  "meikan_url": "https://gakkai.scj.go.jp/organizations/G00688",
  "published_copyright_owner": "学会/出版社",
  "published_licence": "CC BY-SA",
  "published_archivability": "不可",
  "published_location_ir": "",
  "published_location_author": "",
  "published_location_funder": "",
  "published_location_non_commercial": "",
  "published_location_others": "",
  "published_embargo_general_months": "",
  "published_embargo_funded_months": "",
  "published_terms_copyright": "",
  "published_terms_by": "",
  "published_terms_link": "",
  "published_terms_notes": "",
  "accepted_copyright_owner": "学会/出版社",
  "accepted_licence": "著者最終稿にはライセンス情報は設定していません",
  "accepted_archivability": "不可",
  "accepted_location_ir": "",
  "accepted_location_author": "",
  "accepted_location_funder": "",
  "accepted_location_non_commercial": "",
  "accepted_location_others": "",
  "accepted_embargo_general_months": "",
  "accepted_embargo_funded_months": "",
  "accepted_terms_copyright": "",
  "accepted_terms_by": "",
  "accepted_terms_link": "",
  "accepted_terms_notes": "",
  "submitted_archivability": "OK",
  "submitted_location_ir": "OK",
  "submitted_location_author": "OK",
  "submitted_location_funder": "OK",
  "submitted_location_non_commercial": "OK",
  "submitted_location_others": "",
  "submitted_terms_notes": "プレプリントサーバに投稿されている論文が当雑誌に採択・掲載された場合は、掲載され た論文のリンクをプレプリントサーバに載せる。",
  "applicability": "不可",
  "cdjournal": "",
  "updated_at": "2025/09/19"
}