{
  "items": [
    {
      "journal_id": "J000835",
      "titles": [
        {
          "title": "経済教育",
          "language": "ja"
        }
      ],
      "journal_title_alias": null,
      "journal_url": null,
      "issns": [
        {
          "type": "print",
          "issn": "13494058"
        },
        {
          "type": "electronic",
          "issn": "2432-9150"
        }
      ],
      "listed_in_doaj": null,
      "oa_type": null,
      "oa_type_notes": null,
      "non_embargo_oa": null,
      "applicability": null,
      "society": {
        "id": "S000691",
        "name": "経済教育学会",
        "name_en": null,
        "url": "http://www.ecoedu.jp/",
        "contact_url": null,
        "meikan_url": "https://gakkai.scj.go.jp/organizations/G01149"
      },
      "publisher_policy": [
        {
          "article_version": "published",
          "copyright_owner": null,
          "licence": null,
          "archivability": null,
          "location": {
            "ir": null,
            "author": null,
            "funder": null,
            "non_commercial": null,
            "others": null
          },
          "embargo": {
            "general_months": null,
            "funded_months": null
          },
          "terms": {
            "copyright": null,
            "by": null,
            "link": null,
            "notes": null
          }
        },
        {
          "article_version": "accepted",
          "copyright_owner": null,
          "licence": null,
          "archivability": null,
          "location": {
            "ir": null,
            "author": null,
            "funder": null,
            "non_commercial": null,
            "others": null
          },
          "embargo": {
            "general_months": null,
            "funded_months": null
          },
          "terms": {
            "copyright": null,
            "by": null,
            "link": null,
            "notes": null
          }
        },
        {
          "article_version": "submitted",
          "copyright_owner": null,
          "licence": null,
          "archivability": null,
          "location": {
            "ir": null,
            "author": null,
            "funder": null,
            "non_commercial": null,
            "others": null
          },
          "embargo": null,
          "terms": {
            "copyright": null,
            "by": null,
            "link": null,
            "notes": null
          }
        }
      ],
      "policy_url": "http://www.ecoedu.jp/doc/chosakuken.pdf",
      "cdjournal": "ecoedu",
      "updated_at": "2010/12/09",
      "sheet_updated_at": null
    }
  ]
}